kbw-0.1.1.dist-info/LICENSE
kbw-0.1.1.dist-info/RECORD
kbw-0.1.1.dist-info/entry_points.txt
kbw-0.1.1.dist-info/METADATA
kbw-0.1.1.dist-info/WHEEL
kbw-0.1.1.dist-info/top_level.txt
kbw.libs/libuuid-f64cda11.so.1.3.0
kbw/libket_pown.so
kbw/script.py
kbw/libket_mat.so
kbw/__init__.py
kbw/libexample.so
kbw/server.py
kbw/libket_diag.so
kbw/_kbw.so
kbw/kbw.py
kbw/__main__.py
