Metadata-Version: 2.1
Name: kbw
Version: 0.1.1
Summary: Ket Bitwise Simulator Server.
Home-page: https://gitlab.com/quantum-ket/kbw
Author: Evandro Chagas Ribeiro da Rosa
Author-email: evandro.crr@posgrad.ufsc.br
License: Apache-2.0
Platform: UNKNOWN
Classifier: Programming Language :: Python :: 3
Classifier: Programming Language :: C++
Classifier: Intended Audience :: Science/Research
Classifier: Topic :: Scientific/Engineering
Requires-Python: >=3.7
License-File: LICENSE
Requires-Dist: flask (>=2)
Requires-Dist: gevent (>=21.1.2)
